[
 {
  "id": 1,
  "title": "CLASS RESERVATION",
  "teacher": "Pak Aroh",
  "creator": "null",
  "description": "Membuat projek Aplikasi berbasis C#",
  "image_url": "null",
  "repo_link": "https:\/\/github.com\/dashboard",
  "language": "c#\ndesktop"
 },
 {
  "id": 2,
  "title": "CASH MANAGEMENT",
  "teacher": "Pak Aroh",
  "creator": "null",
  "description": "Membuat projek Aplikasi berbasis C#",
  "image_url": "null",
  "repo_link": "https:\/\/github.com\/dashboard",
  "language": "c#\ndesktop"
 },
 {
  "id": 3,
  "title": "TRINITY",
  "teacher": "Pak Aroh",
  "creator": "null",
  "description": "Membuat projek Aplikasi berbasis C#",
  "image_url": "https:\/\/res.cloudinary.com\/dnm8qczle\/image\/upload\/v1759047231\/WhatsApp_Image_2025-02-04_at_20.48.17_934e4325_lgamoi.jpg",
  "repo_link": "https:\/\/github.com\/dashboard",
  "language": "c#\nunity"
 },
 {
  "id": 4,
  "title": "PLANE SHOOTER",
  "teacher": "Pak Aroh",
  "creator": "null",
  "description": "Membuat projek Aplikasi berbasis C#",
  "image_url": "null",
  "repo_link": "https:\/\/github.com\/dashboard",
  "language": "c#\ndesktop"
 },
 {
  "id": 5,
  "title": "Game SUDOKU",
  "teacher": "Pak Aroh",
  "creator": "null",
  "description": "Membuat projek Aplikasi berbasis C#",
  "image_url": "null",
  "repo_link": "https:\/\/github.com\/dashboard",
  "language": "c#\ndesktop"
 },
 {
  "id": 6,
  "title": "SCHOOL LIBRARY",
  "teacher": "Pak Aroh",
  "creator": "null",
  "description": "Membuat projek Aplikasi berbasis C#",
  "image_url": "null",
  "repo_link": "https:\/\/github.com\/dashboard",
  "language": "c#\ndesktop"
 },
 {
  "id": 7,
  "title": "CLASS ABSENCE APP",
  "teacher": "Pak Aroh",
  "creator": "null",
  "description": "Membuat projek Aplikasi berbasis C#",
  "image_url": "null",
  "repo_link": "https:\/\/github.com\/dashboard",
  "language": "c#\ndesktop"
 },
 {
  "id": 8,
  "title": "TYPING TEST",
  "teacher": "Pak Aroh",
  "creator": "null",
  "description": "Membuat projek Aplikasi berbasis C#",
  "image_url": "null",
  "repo_link": "https:\/\/github.com\/dashboard",
  "language": "c#\ndesktop"
 },
 {
  "id": 9,
  "title": "STUDYMATE",
  "teacher": "Pak Aroh",
  "creator": "null",
  "description": "Membuat projek Aplikasi berbasis C#",
  "image_url": "null",
  "repo_link": "https:\/\/github.com\/dashboard",
  "language": "c#\ndesktop"
 },
 {
  "id": 10,
  "title": "ABSENT CLASS PICKET",
  "teacher": "Pak Aroh",
  "creator": "null",
  "description": "Membuat projek Aplikasi berbasis C#",
  "image_url": "null",
  "repo_link": "https:\/\/github.com\/dashboard",
  "language": "c#\ndesktop"
 },
 {
  "id": 11,
  "title": "PHARMACARE",
  "teacher": "Pak Aroh",
  "creator": "null",
  "description": "Membuat projek Aplikasi berbasis C#",
  "image_url": "null",
  "repo_link": "https:\/\/github.com\/dashboard",
  "language": "c#\ndesktop"
 },
 {
  "id": 12,
  "title": "INCOME & EXPENSES TRACKER",
  "teacher": "Pak Aroh",
  "creator": "null",
  "description": "Membuat projek Aplikasi berbasis C#",
  "image_url": "null",
  "repo_link": "https:\/\/github.com\/dashboard",
  "language": "c#\ndesktop"
 },
 {
  "id": 13,
  "title": "CRUD C#",
  "teacher": "Pak Aroh",
  "creator": "null",
  "description": "Mempelajari cara membuat CRUD di C#",
  "image_url": "null",
  "repo_link": "https:\/\/github.com\/dashboard",
  "language": "c#\ndesktop"
 },
 {
  "id": 14,
  "title": "Piano Js",
  "teacher": "Pak Mujahid",
  "creator": "Faqih",
  "description": "Membuat website alat musik pianno yang interaktif",
  "image_url": "https:\/\/res.cloudinary.com\/dnm8qczle\/image\/upload\/v1759046925\/Screenshot_2025-08-18_173544_oqnktx.png",
  "repo_link": "https:\/\/github.com\/LAWAGGG\/Piano-JavaScript",
  "language": "html\ncss\njs"
 },
 {
  "id": 15,
  "title": "Flappy Bird Js",
  "teacher": "Pak Mujahid",
  "creator": "Faqih",
  "description": "Membuat game replikasi Flappy Bird dengan js",
  "image_url": "https:\/\/res.cloudinary.com\/dnm8qczle\/image\/upload\/v1759046938\/Tampilan_v0qzhs.png",
  "repo_link": "https:\/\/github.com\/LAWAGGG\/Flappy_Bird",
  "language": "html\ncss\njs"
 },
 {
  "id": 16,
  "title": "CRUD Js",
  "teacher": "Pak Mujahid",
  "creator": "Faqih",
  "description": "Mempelajari cara membuat CRUD mengambil api php ke js",
  "image_url": "null",
  "repo_link": "https:\/\/github.com\/LAWAGGG\/CRUD-API",
  "language": "html\ncss\njs\nphp"
 },
 {
  "id": 17,
  "title": "Php Dummy Register",
  "teacher": "Pak Mujahid",
  "creator": "null",
  "description": "Mencoba php untuk registrasi",
  "image_url": "https:\/\/res.cloudinary.com\/dnm8qczle\/image\/upload\/v1759047063\/WhatsApp_Image_2025-02-16_at_19.14.46_d9703285_wybdrt.jpg",
  "repo_link": "https:\/\/github.com\/dashboard",
  "language": "html\ncss\nphp"
 },
 {
  "id": 18,
  "title": "Portofolio Bootstrap",
  "teacher": "Pak Mujahid",
  "creator": "Faqih",
  "description": "Membuat portofolio diri sendiri dengan bootstrap",
  "image_url": "https:\/\/res.cloudinary.com\/dnm8qczle\/image\/upload\/v1759047101\/Screenshot_2024-10-27_223158_z5pabi.png",
  "repo_link": "https:\/\/github.com\/LAWAGGG\/Bootstrap-Portofolio",
  "language": "html\nbootstrap"
 },
 {
  "id": 19,
  "title": "Php Autentikasi",
  "teacher": "Pak Mujahid",
  "creator": "null",
  "description": "Membuat pengecekan autentikasi login dengan php native",
  "image_url": "null",
  "repo_link": "https:\/\/github.com\/dashboard",
  "language": "html\ncss\nphp"
 },
 {
  "id": 20,
  "title": "Php OOP CRUD",
  "teacher": "Pak Mujahid",
  "creator": "Faqih",
  "description": "Mempelajari pembuatan CRUD dengan OOP (Object Oriented Programming)",
  "image_url": "https:\/\/res.cloudinary.com\/dnm8qczle\/image\/upload\/v1759043973\/Screenshot_2025-09-28_141909_zgucu8.png",
  "repo_link": "https:\/\/github.com\/LAWAGGG\/CRUD-OOP-PHP",
  "language": "php"
 },
 {
  "id": 21,
  "title": "Php API",
  "teacher": "Pak Mujahid",
  "creator": "Faqih",
  "description": "Membuat rest API dari php native yang bisa digunakan dimana mana",
  "image_url": "https:\/\/res.cloudinary.com\/dnm8qczle\/image\/upload\/v1759044262\/Screenshot_2025-09-28_142411_ijc9jd.png",
  "repo_link": "https:\/\/github.com\/LAWAGGG\/API-Task",
  "language": "php"
 },
 {
  "id": 22,
  "title": "Php MVC",
  "teacher": "Pak Mujahid",
  "creator": "Faqih",
  "description": "Berisi kode php yang sudah dimodifikasi seperti berbentuk framework asli (model, view, controller)",
  "image_url": "https:\/\/res.cloudinary.com\/dnm8qczle\/image\/upload\/v1759042219\/Screenshot_2025-09-28_134944_ppu1j6.png",
  "repo_link": "https:\/\/github.com\/LAWAGGG\/PHP-MVC",
  "language": "html\ncss\nphp"
 },
 {
  "id": 23,
  "title": "RagdollWar",
  "teacher": "Pak Aroh",
  "creator": "Faqih",
  "description": "Membuat projek akhir berbasis aplikasi game unity C#, yaitu game online",
  "image_url": "https:\/\/res.cloudinary.com\/dnm8qczle\/image\/upload\/v1759044016\/Screenshot_2025-04-26_125459_lawamt.png",
  "repo_link": "https:\/\/github.com\/LAWAGGG\/RagdollWar",
  "language": "c#\nunity"
 },
 {
  "id": 24,
  "title": "FastAPI Project",
  "teacher": "Kunjungan Industri",
  "creator": "Faqih",
  "description": "Membuat projek crud dengan bahasa python",
  "image_url": "https:\/\/res.cloudinary.com\/dnm8qczle\/image\/upload\/v1759044211\/Screenshot_2025-09-28_142221_evecgs.png",
  "repo_link": "https:\/\/github.com\/LAWAGGG\/FastAPI-App",
  "language": "python"
 },
 {
  "id": 25,
  "title": "Schopedia",
  "teacher": "Kunjungan Industri",
  "creator": "Kelompok 1",
  "description": "Membuat project aplikasi (mobile & web) marketplace untuk siswa siswi berjualan",
  "image_url": "https:\/\/res.cloudinary.com\/dnm8qczle\/image\/upload\/v1759045493\/Untitled_design_y35gdl.png",
  "repo_link": "https:\/\/github.com\/LAWAGGG\/Schopedia",
  "language": "ReactJs\nLaravel"
 }
]